LICENSE.txt
MANIFEST.in
README.md
setup.py
gsshapy/__init__.py
gsshapy.egg-info/PKG-INFO
gsshapy.egg-info/SOURCES.txt
gsshapy.egg-info/dependency_links.txt
gsshapy.egg-info/requires.txt
gsshapy.egg-info/top_level.txt
gsshapy/base/__init__.py
gsshapy/base/file_base.py
gsshapy/base/geom.py
gsshapy/base/rast.py
gsshapy/grid/__init__.py
gsshapy/grid/era_to_gssha.py
gsshapy/grid/grid_to_gssha.py
gsshapy/grid/hrrr_to_gssha.py
gsshapy/grid/nwm_to_gssha.py
gsshapy/grid/land_cover/land_cover_glcf_modis.txt
gsshapy/grid/land_cover/land_cover_nga.txt
gsshapy/grid/land_cover/land_cover_nlcd.txt
gsshapy/lib/__init__.py
gsshapy/lib/check_geometry.py
gsshapy/lib/cif_chunk.py
gsshapy/lib/cmt_chunk.py
gsshapy/lib/db_tools.py
gsshapy/lib/gag_chunk.py
gsshapy/lib/gsshaDateTime.py
gsshapy/lib/parsetools.py
gsshapy/lib/pivot.py
gsshapy/lib/spn_chunk.py
gsshapy/lib/wms_dataset_chunk.py
gsshapy/modeling/__init__.py
gsshapy/modeling/event.py
gsshapy/modeling/framework.py
gsshapy/modeling/model.py
gsshapy/orm/__init__.py
gsshapy/orm/cif.py
gsshapy/orm/cmt.py
gsshapy/orm/ele.py
gsshapy/orm/evt.py
gsshapy/orm/file_io.py
gsshapy/orm/gag.py
gsshapy/orm/generic.py
gsshapy/orm/gpi.py
gsshapy/orm/gst.py
gsshapy/orm/hmet.py
gsshapy/orm/idx.py
gsshapy/orm/lnd.py
gsshapy/orm/loc.py
gsshapy/orm/map.py
gsshapy/orm/msk.py
gsshapy/orm/prj.py
gsshapy/orm/pro.py
gsshapy/orm/rep.py
gsshapy/orm/snw.py
gsshapy/orm/spn.py
gsshapy/orm/tim.py
gsshapy/orm/wms_dataset.py
gsshapy/util/__init__.py
gsshapy/util/context.py
gsshapy/util/log.py
gsshapy/util/metadata.py