Metadata-Version: 2.1
Name: gsshapy
Version: 2.3.9
Summary: An SQLAlchemy ORM for GSSHA model files and a toolkit to convert gridded input into GSSHA input.
Home-page: https://github.com/CI-WATER/gsshapy
Author: Nathan Swain, Alan D. Snow, and Scott D. Christensen
Author-email: nathan.swain@byu.net
License: BSD 3-Clause License
Keywords: GSSHA,database,object relational model
Platform: UNKNOWN
Classifier: Intended Audience :: Developers
Classifier: Intended Audience :: Science/Research
Classifier: Operating System :: OS Independent
Classifier: Programming Language :: Python
Classifier: Programming Language :: Python :: 2
Classifier: Programming Language :: Python :: 2.7
Classifier: Programming Language :: Python :: 3
Classifier: Programming Language :: Python :: 3.5
Provides-Extra: tests
Provides-Extra: docs
